
{
  "data": [
   {
      "id":"id1",
      "code":"code1",
      "name":"Role1",
      "description":"test description Role1",
      "status":1,
      "level":"99"
   },
   {
      "id":"id2",
      "code":"code2",
      "name":"Role2",
      "description":"test description Role2",
      "status":0,
      "level":"99"
   },
   {
      "id":"id3",
      "code":"code3",
      "name":"Role3",
      "description":"test description Role3",
      "status":1,
      "level":"99"
   },
   {
      "id":"id4",
      "code":"code4",
      "name":"Role4",
      "description":"test description Role4",
      "status":0,
      "level":"99"
   },
   {
      "id":"id5",
      "code":"code5",
      "name":"Role5",
      "description":"test description Role5",
      "status":1,
      "level":"99"
   },
   {
      "id":"id6",
      "code":"code6",
      "name":"Role6",
      "description":"test description Role6",
      "status":0,
      "level":"99"
   },
   {
      "id":"id7",
      "code":"code7",
      "name":"Role7",
      "description":"test description Role7",
      "status":1,
      "level":"99"
   },
   {
      "id":"id8",
      "code":"code8",
      "name":"Role8",
      "description":"test description Role8",
      "status":0,
      "level":"99"
   },
   {
      "id":"id9",
      "code":"code9",
      "name":"Role9",
      "description":"test description Role9",
      "status":1,
      "level":"99"
   },
   {
      "id":"id10",
      "code":"code10",
      "name":"Role10",
      "description":"test description Role10",
      "status":0,
      "level":"99"
   },
    {
      "id":"id11",
      "code":"code11",
      "name":"Role11",
      "description":"test description Role11",
      "status":1,
      "level":"99"
   },
   {
      "id":"id12",
      "code":"code12",
      "name":"Role12",
      "description":"test description Role12",
      "status":0,
      "level":"99"
   },
   {
      "id":"id13",
      "code":"code13",
      "name":"Role13",
      "description":"test description Role13",
      "status":1,
      "level":"99"
   },
   {
      "id":"id14",
      "code":"code14",
      "name":"Role14",
      "description":"test description Role14",
      "status":0,
      "level":"99"
   },
   {
      "id":"id15",
      "code":"code15",
      "name":"Role15",
      "description":"test description Role15",
      "status":1,
      "level":"99"
   },
    {
      "id":"id16",
      "code":"code16",
      "name":"Role16",
      "description":"test description Role16",
      "status":0,
      "level":"99"
   },
   {
      "id":"id17",
      "code":"code17",
      "name":"Role17",
      "description":"test description Role17",
      "status":1,
      "level":"99"
   },
   {
      "id":"id18",
      "code":"code18",
      "name":"Role18",
      "description":"test description Role18",
      "status":0,
      "level":"99"
   },
   {
      "id":"id19",
      "code":"code19",
      "name":"Role19",
      "description":"test description Role19",
      "status":1,
      "level":"99"
   },
   {
      "id":"id20",
      "code":"code20",
      "name":"Role20",
      "description":"test description Role20",
      "status":0,
      "level":"99"
   }
  ],
  "roleUserData": [{"userId":"id1","employeeId":"employee id1","locaFirstName":"local first name1","localLastName":"local last name1","firstName":"first name1","lastName":"last name1"},{"userId":"id2","employeeId":"employee id2","locaFirstName":"local first name2","localLastName":"local last name2","firstName":"first name2","lastName":"last name2"},{"userId":"id3","employeeId":"employee id3","locaFirstName":"local first name3","localLastName":"local last name3","firstName":"first name3","lastName":"last name3"},{"userId":"id4","employeeId":"employee id4","locaFirstName":"local first name4","localLastName":"local last name4","firstName":"first name4","lastName":"last name4"},{"userId":"id5","employeeId":"employee id5","locaFirstName":"local first name5","localLastName":"local last name5","firstName":"first name5","lastName":"last name5"},{"userId":"id6","employeeId":"employee id6","locaFirstName":"local first name6","localLastName":"local last name6","firstName":"first name6","lastName":"last name6"},{"userId":"id7","employeeId":"employee id7","locaFirstName":"local first name7","localLastName":"local last name7","firstName":"first name7","lastName":"last name7"},{"userId":"id8","employeeId":"employee id8","locaFirstName":"local first name8","localLastName":"local last name8","firstName":"first name8","lastName":"last name8"},{"userId":"id9","employeeId":"employee id9","locaFirstName":"local first name9","localLastName":"local last name9","firstName":"first name9","lastName":"last name9"},{"userId":"id10","employeeId":"employee id10","locaFirstName":"local first name10","localLastName":"local last name10","firstName":"first name10","lastName":"last name10"},{"userId":"id11","employeeId":"employee id11","locaFirstName":"local first name11","localLastName":"local last name11","firstName":"first name11","lastName":"last name11"},{"userId":"id12","employeeId":"employee id12","locaFirstName":"local first name12","localLastName":"local last name12","firstName":"first name12","lastName":"last name12"},{"userId":"id13","employeeId":"employee id13","locaFirstName":"local first name13","localLastName":"local last name13","firstName":"first name13","lastName":"last name13"},{"userId":"id14","employeeId":"employee id14","locaFirstName":"local first name14","localLastName":"local last name14","firstName":"first name14","lastName":"last name14"},{"userId":"id15","employeeId":"employee id15","locaFirstName":"local first name15","localLastName":"local last name15","firstName":"first name15","lastName":"last name15"},{"userId":"id16","employeeId":"employee id16","locaFirstName":"local first name16","localLastName":"local last name16","firstName":"first name16","lastName":"last name16"},{"userId":"id17","employeeId":"employee id17","locaFirstName":"local first name17","localLastName":"local last name17","firstName":"first name17","lastName":"last name17"},{"userId":"id18","employeeId":"employee id18","locaFirstName":"local first name18","localLastName":"local last name18","firstName":"first name18","lastName":"last name18"},{"userId":"id19","employeeId":"employee id19","locaFirstName":"local first name19","localLastName":"local last name19","firstName":"first name19","lastName":"last name19"},{"userId":"id20","employeeId":"employee id20","locaFirstName":"local first name20","localLastName":"local last name20","firstName":"first name20","lastName":"last name20"},{"userId":"id21","employeeId":"employee id21","locaFirstName":"local first name21","localLastName":"local last name21","firstName":"first name21","lastName":"last name21"},{"userId":"id22","employeeId":"employee id22","locaFirstName":"local first name22","localLastName":"local last name22","firstName":"first name22","lastName":"last name22"},{"userId":"id23","employeeId":"employee id23","locaFirstName":"local first name23","localLastName":"local last name23","firstName":"first name23","lastName":"last name23"},{"userId":"id24","employeeId":"employee id24","locaFirstName":"local first name24","localLastName":"local last name24","firstName":"first name24","lastName":"last name24"},{"userId":"id25","employeeId":"employee id25","locaFirstName":"local first name25","localLastName":"local last name25","firstName":"first name25","lastName":"last name25"}],
  "userUserData": [
   {
      "status":"active",
      "employeeNo":"11025996",
      "firstname":"first",
      "lastname":"วงศ์มณีรัตน์",
      "createdDate":"14/05/2020",
      "modifiedDate":"14/05/2020",
      "effectiveFrom":"01/05/2020",
      "effectiveTo":"",
      "role":"152"
   },
   {
      "status":"inactive",
      "employeeNo":"11025996",
      "firstname":"second",
      "lastname":"วงศ์มณีรัตน์",
      "createdDate":"14/05/2020",
      "modifiedDate":"14/05/2020",
      "effectiveFrom":"01/05/2020",
      "effectiveTo":"",
      "role":"152"
   }
  ],
  "addSysUser": [
    {
      "contactId": "000001",
      "employeeNo": "987654",
      "firstName": "หนึ่ง",
      "lastName": "ถนอมดี",
      "company": "Outsource",
      "department": "สำนักงานสารสนเทศ",
      "deptAddress": "อาคาร เล้าเป้งง้วน 1"
    },
    {
      "contactId": "000002",
      "employeeNo": "987654",
      "firstName": "สอง",
      "lastName": "ถนอมดี",
      "company": "Outsource",
      "department": "สำนักงานสารสนเทศ",
      "deptAddress": "อาคาร เล้าเป้งง้วน 1"
    },
    {
      "contactId": "000003",
      "employeeNo": "987654",
      "firstName": "สาม",
      "lastName": "ถนอมดี",
      "company": "Outsource",
      "department": "สำนักงานสารสนเทศ",
      "deptAddress": "อาคาร เล้าเป้งง้วน 1"
    },
    {
      "contactId": "000004",
      "employeeNo": "987654",
      "firstname": "สี่",
      "lastName": "ถนอมดี",
      "company": "Outsource",
      "department": "สำนักงานสารสนเทศ",
      "deptAddress": "อาคาร เล้าเป้งง้วน 1"
    },
    {
      "contactId": "000005",
      "employeeNo": "987654",
      "firstName": "ห้า",
      "lastName": "ถนอมดี",
      "company": "Outsource",
      "department": "สำนักงานสารสนเทศ",
      "deptAddress": "อาคาร เล้าเป้งง้วน 1"
    },
    {
      "contactId": "000006",
      "employeeNo": "987654",
      "firstName": "หก",
      "lastName": "ถนอมดี",
      "company": "Outsource",
      "department": "สำนักงานสารสนเทศ",
      "deptAddress": "อาคาร เล้าเป้งง้วน 1"
    },
    {
      "contactId": "000007",
      "employeeNo": "987654",
      "firstName": "เจ็ด",
      "lastName": "ถนอมดี",
      "company": "Outsource",
      "department": "สำนักงานสารสนเทศ",
      "deptAddress": "อาคาร เล้าเป้งง้วน 1"
    }
  ]
}
